utils4plans/__init__.py
utils4plans/geom.py
utils4plans/graphs.py
utils4plans/io.py
utils4plans/lists.py
utils4plans/logconfig.py
utils4plans/paths.py
utils4plans/printing.py
utils4plans/py.typed
utils4plans/sets.py
utils4plans-0.1.12.dist-info/METADATA
utils4plans-0.1.12.dist-info/WHEEL
utils4plans-0.1.12.dist-info/RECORD
