Metadata-Version: 2.4
Name: utils4plans
Version: 0.1.12
Summary: Helpers for manipulating floorplan geometries
Author-email: Juliet Nwagwu Ume-Ezeoke <jnwagwu@stanford.edu>
Requires-Python: >=3.13
Requires-Dist: expression>=5.6.0
Requires-Dist: loguru>=0.7.3
Requires-Dist: networkx>=3.5
Requires-Dist: numpy>=2.3.2
Requires-Dist: pytest>=8.4.1
Requires-Dist: rich>=14.1.0
Requires-Dist: tomli-w>=1.2.0
